.gitignore
.readthedocs.yml
CHANGES.rst
MANIFEST.in
README.rst
conda-environment.yml
pyproject.toml
setup.cfg
setup.py
tox.ini
.github/workflows/tox-tests.yml
beast/.gitignore
beast/README.rst
beast/__init__.py
beast/config.py
beast/conftest.py
beast/main.py
beast/version.py
beast.egg-info/PKG-INFO
beast.egg-info/SOURCES.txt
beast.egg-info/dependency_links.txt
beast.egg-info/entry_points.txt
beast.egg-info/not-zip-safe
beast.egg-info/requires.txt
beast.egg-info/top_level.txt
beast/fitting/__init__.py
beast/fitting/fit.py
beast/fitting/pdf1d.py
beast/fitting/pdf2d.py
beast/fitting/trim_grid.py
beast/fitting/fit_metrics/__init__.py
beast/fitting/fit_metrics/common.py
beast/fitting/fit_metrics/likelihood.py
beast/fitting/tests/__init__.py
beast/observationmodel/__init__.py
beast/observationmodel/extra_filters.py
beast/observationmodel/observations.py
beast/observationmodel/phot.py
beast/observationmodel/vega.py
beast/observationmodel/ast/__init__.py
beast/observationmodel/ast/make_ast_input_list.py
beast/observationmodel/ast/make_ast_xy_list.py
beast/observationmodel/noisemodel/__init__.py
beast/observationmodel/noisemodel/absflux_covmat.py
beast/observationmodel/noisemodel/generic_noisemodel.py
beast/observationmodel/noisemodel/helpers.py
beast/observationmodel/noisemodel/noisemodel.py
beast/observationmodel/noisemodel/splinter.py
beast/observationmodel/noisemodel/toothpick.py
beast/observationmodel/noisemodel/trunchen.py
beast/observationmodel/noisemodel/tests/__init__.py
beast/observationmodel/noisemodel/tests/test_splinter_noisemodel.py
beast/observationmodel/tests/__init__.py
beast/observationmodel/tests/test_extra_filters.py
beast/observationmodel/tests/test_filters_and_vega_consistent.py
beast/physicsmodel/__init__.py
beast/physicsmodel/create_project_dir.py
beast/physicsmodel/creategrid.py
beast/physicsmodel/grid.py
beast/physicsmodel/grid_and_prior_weights.py
beast/physicsmodel/grid_weights.py
beast/physicsmodel/model_grid.py
beast/physicsmodel/priormodel.py
beast/physicsmodel/priormodel_functions.py
beast/physicsmodel/dust/__init__.py
beast/physicsmodel/dust/extinction.py
beast/physicsmodel/dust/extinction_extension.py
