Metadata-Version: 2.4
Name: beast
Version: 2.1.0
Summary: Bayesian Extinction and Stellar Tool
Home-page: http://beast.readthedocs.io/
Author: Karl Gordon and BEAST Team
Author-email: kgordon@stsci.edu
License: BSD 3-Clause
Requires-Python: >=3.8
License-File: licenses/LICENSE.rst
Requires-Dist: numpy
Requires-Dist: astropy
Requires-Dist: Cython
Requires-Dist: scipy
Requires-Dist: matplotlib
Requires-Dist: h5py
Requires-Dist: tables
Requires-Dist: dust_extinction
Requires-Dist: tqdm
Requires-Dist: photutils
Requires-Dist: shapely
Requires-Dist: graphviz
Requires-Dist: asdf
Requires-Dist: stsynphot
Requires-Dist: pandeia.engine
Requires-Dist: importlib_resources
Provides-Extra: test
Requires-Dist: pytest-astropy; extra == "test"
Provides-Extra: docs
Requires-Dist: sphinx-astropy; extra == "docs"
Dynamic: license-file
